rtpi/__init__.py
rtpi/providers/__init__.py
rtpi/providers/irishrail.py
rtpi/providers/smartdublin.py
rtpi-0.1.3.dist-info/WHEEL
rtpi-0.1.3.dist-info/METADATA
rtpi-0.1.3.dist-info/RECORD
