Metadata-Version: 2.1
Name: rtpi
Version: 0.1.3
Summary: 
Author: Marco Rougeth
Author-email: marco@rougeth.com
Requires-Python: >=3.7,<4.0
Classifier: Programming Language :: Python :: 3
Classifier: Programming Language :: Python :: 3.7
Classifier: Programming Language :: Python :: 3.8
Requires-Dist: httpx (>=0.11.1,<0.12.0)
